industrial_benchmark_python/EffectiveAction.py
industrial_benchmark_python/IBGym.py
industrial_benchmark_python/IDS.py
industrial_benchmark_python/__init__.py
industrial_benchmark_python/example.py
industrial_benchmark_python/test_baselines.py
industrial_benchmark_python/test_industrial_benchmark_python.py
industrial_benchmark_python/goldstone/__init__.py
industrial_benchmark_python/goldstone/dynamics.py
industrial_benchmark_python/goldstone/environment.py
industrial_benchmark_python/goldstone/nlgp.py
industrial_benchmark_python/goldstone/reward_function.py
industrial_benchmark_python-2.0.dist-info/LICENCE.txt
industrial_benchmark_python-2.0.dist-info/METADATA
industrial_benchmark_python-2.0.dist-info/WHEEL
industrial_benchmark_python-2.0.dist-info/top_level.txt
industrial_benchmark_python-2.0.dist-info/RECORD
