Metadata-Version: 2.1
Name: industrial-benchmark-python
Version: 2.0
Summary: the industrial benchmark as a python package
Home-page: https://github.com/siemens/industrialbenchmark.git
Author: Daniel Hein, Stefan Depeweg, Michel Tokic, Steffen Udluft, Alexander Hentschel, Phillip Swazinna
Author-email: hein.daniel@siemens.com
License: UNKNOWN
Platform: UNKNOWN
Classifier: Programming Language :: Python :: 3
Classifier: License :: OSI Approved :: MIT License
Classifier: Operating System :: OS Independent
Requires-Python: >=3.6
Requires-Dist: gym
Requires-Dist: numpy
